ckeditor_filebrowser_filer/__init__.py
ckeditor_filebrowser_filer/models.py
ckeditor_filebrowser_filer/urls.py
ckeditor_filebrowser_filer/views.py
ckeditor_filebrowser_filer/static/admin/img/icon_deletelink.gif
ckeditor_filebrowser_filer/static/admin/img/icon_searchbox.png
ckeditor_filebrowser_filer/static/ckeditor/ckeditor/plugins/filerimage/plugin.js
ckeditor_filebrowser_filer/static/ckeditor/ckeditor/plugins/filerimage/dialogs/filerImageDialog.js
ckeditor_filebrowser_filer/static/ckeditor/ckeditor/plugins/filerimage/icons/filerimage.png
ckeditor_filebrowser_filer/static/ckeditor/ckeditor/plugins/filerimage/lang/en.js
ckeditor_filebrowser_filer/static/ckeditor/ckeditor/plugins/filerimage/lang/fr.js
ckeditor_filebrowser_filer/static/ckeditor/ckeditor/plugins/filerimage/lang/it.js
ckeditor_filebrowser_filer/static/ckeditor/ckeditor/plugins/filerimage/lang/ru.js
ckeditor_filebrowser_filer/static/djangocms_text_ckeditor/ckeditor/plugins/filerimage/plugin.js
ckeditor_filebrowser_filer/static/djangocms_text_ckeditor/ckeditor/plugins/filerimage/dialogs/filerImageDialog.js
ckeditor_filebrowser_filer/static/djangocms_text_ckeditor/ckeditor/plugins/filerimage/icons/filerimage.png
ckeditor_filebrowser_filer/static/djangocms_text_ckeditor/ckeditor/plugins/filerimage/lang/en.js
ckeditor_filebrowser_filer/static/djangocms_text_ckeditor/ckeditor/plugins/filerimage/lang/fr.js
ckeditor_filebrowser_filer/static/djangocms_text_ckeditor/ckeditor/plugins/filerimage/lang/it.js
ckeditor_filebrowser_filer/static/djangocms_text_ckeditor/ckeditor/plugins/filerimage/lang/ru.js
django_ckeditor_filebrowser_filer-0.5.0.dist-info/LICENSE
django_ckeditor_filebrowser_filer-0.5.0.dist-info/METADATA
django_ckeditor_filebrowser_filer-0.5.0.dist-info/WHEEL
django_ckeditor_filebrowser_filer-0.5.0.dist-info/top_level.txt
django_ckeditor_filebrowser_filer-0.5.0.dist-info/RECORD
