Metadata-Version: 2.1
Name: django-ckeditor-filebrowser-filer
Version: 0.5.0
Summary: A django-filer based CKEditor filebrowser
Home-page: https://github.com/nephila/django-ckeditor-filebrowser-filer
Author: Iacopo Spalletti
Author-email: i.spalletti@nephila.it
License: BSD
Classifier: License :: OSI Approved :: BSD License
Classifier: Development Status :: 5 - Production/Stable
Classifier: Framework :: Django
Classifier: Framework :: Django :: 3.2
Classifier: Framework :: Django :: 4.1
Classifier: Framework :: Django :: 4.2
Classifier: Programming Language :: Python
Classifier: Programming Language :: Python :: 3
Classifier: Programming Language :: Python :: 3.7
Classifier: Programming Language :: Python :: 3.8
Classifier: Programming Language :: Python :: 3.9
Classifier: Programming Language :: Python :: 3.10
Classifier: Programming Language :: Python :: 3.11
Requires-Python: >=3.7
License-File: LICENSE
Requires-Dist: django-filer >=2.0
